pyworks_generator/__init__.py
pyworks_generator/__main__.py
pyworks_generator/api.yaml
pyworks_generator/format.py
pyworks_generator/http.py
pyworks_generator/imports.py
pyworks_generator/reference.py
pyworks_generator/types.py
pyworks_generator/version.py
pyworks_generator/model/__init__.py
pyworks_generator/model/base.py
pyworks_generator/model/enum.py
pyworks_generator/model/pydantic/__init__.py
pyworks_generator/model/pydantic/base_model.py
pyworks_generator/model/pydantic/custom_root_type.py
pyworks_generator/model/pydantic/dataclass.py
pyworks_generator/model/pydantic/imports.py
pyworks_generator/model/pydantic/types.py
pyworks_generator/model/template/Enum.jinja2
pyworks_generator/model/template/pydantic/BaseModel.jinja2
pyworks_generator/model/template/pydantic/BaseModel_root.jinja2
pyworks_generator/model/template/pydantic/Config.jinja2
pyworks_generator/model/template/pydantic/dataclass.jinja2
pyworks_generator/parser/__init__.py
pyworks_generator/parser/base.py
pyworks_generator/parser/jsonschema.py
pyworks_generator/parser/openapi.py
tests/__init__.py
tests/test_imports.py
tests/test_main.py
tests/test_main_kr.py
tests/data/pyproject.toml
tests/data/csv/simple.csv
tests/data/expected/main/all_of_ref/output.py
tests/data/expected/main/allow_population_by_field_name/output.py
tests/data/expected/main/csv_file_simple/output.py
tests/data/expected/main/csv_stdin_simple/output.py
tests/data/expected/main/disable_timestamp/output.py
tests/data/expected/main/enable_faux_immutability/output.py
tests/data/expected/main/force_optional/output.py
tests/data/expected/main/main/output.py
tests/data/expected/main/main_autodetect/output.py
tests/data/expected/main/main_base_class/output.py
tests/data/expected/main/main_circular_reference/output.py
tests/data/expected/main/main_complicated_enum_default_member/output.py
tests/data/expected/main/main_custom_template_dir/output.py
tests/data/expected/main/main_disable_appending_item_suffix/output.py
pyworks_generator-0.1.0.dist-info/LICENSE
pyworks_generator-0.1.0.dist-info/METADATA
pyworks_generator-0.1.0.dist-info/WHEEL
pyworks_generator-0.1.0.dist-info/entry_points.txt
pyworks_generator-0.1.0.dist-info/top_level.txt
pyworks_generator-0.1.0.dist-info/zip-safe
pyworks_generator-0.1.0.dist-info/RECORD
