Metadata-Version: 2.1
Name: pyworks-generator
Version: 0.1.0
Summary: PyWorks Code Generator
Home-page: https://github.com/pyworksasia/pyworks-generator
Author: PyWorks
Author-email: pyworksasia@gmail.com
License: UNKNOWN
Platform: UNKNOWN
Classifier: Development Status :: 4 - Beta
Classifier: Natural Language :: English
Classifier: License :: OSI Approved :: MIT License
Classifier: Programming Language :: Python :: 3
Classifier: Programming Language :: Python :: 3.6
Classifier: Programming Language :: Python :: 3.7
Classifier: Programming Language :: Python :: 3.8
Classifier: Programming Language :: Python :: 3.9
Classifier: Programming Language :: Python :: Implementation :: CPython
Requires-Python: >=3.6.1
Requires-Dist: PySnooper (<1.0.0,>=0.4.1)
Requires-Dist: argcomplete (<2.0,>=1.10)
Requires-Dist: black (>=19.10b0)
Requires-Dist: genson (<2.0,>=1.2.1)
Requires-Dist: inflect (<6.0,>=4.1.0)
Requires-Dist: isort (<6.0,>=4.3.21)
Requires-Dist: jinja2 (<3.0,>=2.10.1)
Requires-Dist: openapi-spec-validator (<0.4,>=0.2.8)
Requires-Dist: prance (<1.0,>=0.18.2)
Requires-Dist: toml (<1.0.0,>=0.10.0)
Requires-Dist: pydantic[email] (<2.0,>=1.5.1) ; python_version < "3.9"
Requires-Dist: pydantic[email] (<2.0,>=1.7.2) ; python_version >= "3.9"
Provides-Extra: all
Requires-Dist: codecov ; extra == 'all'
Requires-Dist: freezegun ; extra == 'all'
Requires-Dist: httpx ; extra == 'all'
Requires-Dist: isort ; extra == 'all'
Requires-Dist: mkdocs ; extra == 'all'
Requires-Dist: mkdocs-material ; extra == 'all'
Requires-Dist: mypy ; extra == 'all'
Requires-Dist: pytest-benchmark ; extra == 'all'
Requires-Dist: pytest-cov ; extra == 'all'
Requires-Dist: pytest-mock ; extra == 'all'
Requires-Dist: pytest-runner ; extra == 'all'
Requires-Dist: pytest (>=4.6) ; extra == 'all'
Requires-Dist: setuptools-scm ; extra == 'all'
Requires-Dist: twine ; extra == 'all'
Requires-Dist: wheel ; extra == 'all'
Provides-Extra: ci
Requires-Dist: codecov ; extra == 'ci'
Provides-Extra: docs
Requires-Dist: mkdocs ; extra == 'docs'
Requires-Dist: mkdocs-material ; extra == 'docs'
Provides-Extra: http
Requires-Dist: httpx ; extra == 'http'
Provides-Extra: setup
Requires-Dist: pytest-runner ; extra == 'setup'
Requires-Dist: setuptools-scm ; extra == 'setup'
Provides-Extra: test
Requires-Dist: freezegun ; extra == 'test'
Requires-Dist: isort ; extra == 'test'
Requires-Dist: mypy ; extra == 'test'
Requires-Dist: pytest-benchmark ; extra == 'test'
Requires-Dist: pytest-cov ; extra == 'test'
Requires-Dist: pytest-mock ; extra == 'test'
Requires-Dist: pytest (>=4.6) ; extra == 'test'
Provides-Extra: wheel
Requires-Dist: twine ; extra == 'wheel'
Requires-Dist: wheel ; extra == 'wheel'
